tradesignals/__init__.py
tradesignals/_base_client.py
tradesignals/_client.py
tradesignals/_compat.py
tradesignals/_constants.py
tradesignals/_exceptions.py
tradesignals/_files.py
tradesignals/_models.py
tradesignals/_qs.py
tradesignals/_resource.py
tradesignals/_response.py
tradesignals/_streaming.py
tradesignals/_types.py
tradesignals/_version.py
tradesignals/py.typed
tradesignals/_utils/__init__.py
tradesignals/_utils/_logs.py
tradesignals/_utils/_proxy.py
tradesignals/_utils/_reflection.py
tradesignals/_utils/_streams.py
tradesignals/_utils/_sync.py
tradesignals/_utils/_transform.py
tradesignals/_utils/_typing.py
tradesignals/_utils/_utils.py
tradesignals/lib/.keep
tradesignals/resources/__init__.py
tradesignals/resources/correlations.py
tradesignals/resources/darkpool.py
tradesignals/resources/news.py
tradesignals/resources/analyst/__init__.py
tradesignals/resources/analyst/analyst.py
tradesignals/resources/analyst/ratings.py
tradesignals/resources/analyst/upgrades_downgrades.py
tradesignals/resources/congress/__init__.py
tradesignals/resources/congress/congress.py
tradesignals/resources/congress/members.py
tradesignals/resources/congress/trades.py
tradesignals/resources/economic_calendars/__init__.py
tradesignals/resources/economic_calendars/economic_calendars.py
tradesignals/resources/economic_calendars/fda_calendar.py
tradesignals/resources/etf/__init__.py
tradesignals/resources/etf/etf.py
tradesignals/resources/etf/holdings.py
tradesignals/resources/etf/sectors.py
tradesignals/resources/etf/tide.py
tradesignals/resources/insider_trades/__init__.py
tradesignals/resources/insider_trades/insider_trades.py
tradesignals/resources/insider_trades/trades.py
tradesignals/resources/institutions/__init__.py
tradesignals/resources/institutions/institutional_activities.py
tradesignals/resources/institutions/institutions.py
tradesignals/resources/institutions/trades.py
tradesignals/resources/market/__init__.py
tradesignals/resources/market/indices.py
tradesignals-0.1.0a3.dist-info/METADATA
tradesignals-0.1.0a3.dist-info/WHEEL
tradesignals-0.1.0a3.dist-info/licenses/LICENSE
tradesignals-0.1.0a3.dist-info/RECORD
